CREDITS.rst
LICENSE_GPL2.0.txt
LICENSE_LGPL_2.1.txt
MANIFEST.in
README.rst
setup.py
src/starbase/__init__.py
src/starbase/conf.py
src/starbase/content_types.py
src/starbase/defaults.py
src/starbase/exceptions.py
src/starbase/translations.py
src/starbase.egg-info/PKG-INFO
src/starbase.egg-info/SOURCES.txt
src/starbase.egg-info/dependency_links.txt
src/starbase.egg-info/requires.txt
src/starbase.egg-info/top_level.txt
src/starbase/client/__init__.py
src/starbase/client/connection.py
src/starbase/client/helpers.py
src/starbase/client/scanner_test.py
src/starbase/client/speed_test.py
src/starbase/client/tests.py
src/starbase/client/table/__init__.py
src/starbase/client/table/batch.py
src/starbase/client/table/query.py
src/starbase/client/table/scanner.py
src/starbase/client/transport/__init__.py
src/starbase/client/transport/methods.py
src/starbase/client/transport/status_codes.py
src/starbase/json_decoder/__init__.py
src/starbase/json_decoder/tests.py
src/starbase/server/__init__.py
src/starbase/server/runserver.py