Metadata-Version: 1.1
Name: starbase
Version: 0.3
Summary: Python client for HBase Stargate REST server
Home-page: https://github.com/barseghyanartur/starbase
Author: Artur Barseghyan
Author-email: artur.barseghyan@gmail.com
License: GPL 2.0/LGPL 2.1
Keywords: hadoop,hbase,stargate,app,python
Platform: UNKNOWN
Classifier: Programming Language :: Python
Classifier: Programming Language :: Python :: 2.6
Classifier: Programming Language :: Python :: 2.7
Classifier: Programming Language :: Python :: 3
Classifier: Programming Language :: Python :: 3.3
Classifier: License :: OSI Approved :: GNU General Public License v2 (GPLv2)
Classifier: License :: OSI Approved :: GNU Lesser General Public License v2 or later (LGPLv2+)
Classifier: Environment :: Web Environment
Classifier: Intended Audience :: Developers
Classifier: Operating System :: OS Independent
Classifier: Development Status :: 4 - Beta
Classifier: Topic :: Database
